thonnycontrib/ThonnyLogsGenerator.py
thonnycontrib/__init__.py
thonnycontrib/environement_vars.py
thonnycontrib/exceptions.py
thonnycontrib/plugin_loader.py
thonnycontrib/properties.py
thonnycontrib/utils.py
thonnycontrib/backend/__init__.py
thonnycontrib/backend/ast_parser.py
thonnycontrib/backend/doctest_parser.py
thonnycontrib/backend/evaluator.py
thonnycontrib/backend/l1test_backend.py
thonnycontrib/backend/test_finder.py
thonnycontrib/backend/verdicts/ExampleVerdict.py
thonnycontrib/backend/verdicts/ExceptionVerdict.py
thonnycontrib/backend/verdicts/FailedVerdict.py
thonnycontrib/backend/verdicts/FailedWhenExceptionExpectedVerdict.py
thonnycontrib/backend/verdicts/PassedSetupVerdict.py
thonnycontrib/backend/verdicts/PassedVerdict.py
thonnycontrib/backend/verdicts/__init__.py
thonnycontrib/frontend/__init__.py
thonnycontrib/frontend/l1test_error_view.py
thonnycontrib/frontend/l1test_outliner_menu.py
thonnycontrib/frontend/l1test_reporter.py
thonnycontrib/frontend/l1test_runner.py
thonnycontrib/frontend/l1test_treeview.py
thonnycontrib/frontend/docstring_generator/__init__.py
thonnycontrib/frontend/docstring_generator/doc_generator.py
thonnycontrib/frontend/docstring_generator/doc_template.py
thonnycontrib/frontend/main_generator/__init__.py
thonnycontrib/frontend/main_generator/main_generator.py
thonnycontrib/i18n/__init__.py
thonnycontrib/i18n/languages.py
thonnycontrib/i18n/locale/l1test.pot
thonnycontrib/i18n/locale/en_US/LC_MESSAGES/l1test.mo
thonnycontrib/i18n/locale/en_US/LC_MESSAGES/l1test.po
thonnycontrib/i18n/locale/fr_FR/LC_MESSAGES/l1test.mo
thonnycontrib/i18n/locale/fr_FR/LC_MESSAGES/l1test.po
thonnycontrib/img/error_icon.png
thonnycontrib/img/exception_red_chip.png
thonnycontrib/img/failed.png
thonnycontrib/img/failed_red_chip.png
thonnycontrib/img/l1test_icon.png
thonnycontrib/img/l1test_icon_old.png
thonnycontrib/img/outline_class.png
thonnycontrib/img/outline_method.gif
thonnycontrib/img/passed.png
thonnycontrib/img/pending_icon.png
bimbam-6.998.dist-info/METADATA
bimbam-6.998.dist-info/WHEEL
bimbam-6.998.dist-info/top_level.txt
bimbam-6.998.dist-info/RECORD
