Metadata-Version: 2.1
Name: bimbam
Version: 6.998
Summary: A plug-in which adds a test framework
Home-page: https://gitlab.univ-lille.fr/mirabelle.nebut/thonny-tests
Author: idtaleb
Platform: Windows
Platform: macOS
Platform: Linux
Classifier: Topic :: Education :: Testing
Classifier: Programming Language :: Python :: 3
Classifier: License :: OSI Approved :: MIT License
Classifier: Operating System :: OS Independent
Classifier: Development Status :: 3 - Alpha
Classifier: Intended Audience :: Education
Requires-Python: >=3.9
Requires-Dist: thonny (>=4.0.0)
